README.md
README.rst
setup.py
weightunit/__init__.py
weightunit.egg-info/PKG-INFO
weightunit.egg-info/SOURCES.txt
weightunit.egg-info/dependency_links.txt
weightunit.egg-info/top_level.txt