Metadata-Version: 2.1
Name: weightunit
Version: 0.0.4
Summary: 提取淘宝title中的单位字符串，并且进行重量计算
Home-page: https://github.com/chongwangcc/weightunit
Author: chongwangcc
Author-email: chongwangcc@gmail.com
License: UNKNOWN
Platform: UNKNOWN
